nonebot_plugin_wordle_daily/__init__.py
nonebot_plugin_wordle_daily/assets/ClearSans-Bold.ttf
nonebot_plugin_wordle_daily/consts.py
nonebot_plugin_wordle_daily/deps.py
nonebot_plugin_wordle_daily/image.py
nonebot_plugin_wordle_daily/util.py
nonebot_plugin_wordle_daily-0.1.0.dist-info/WHEEL
nonebot_plugin_wordle_daily-0.1.0.dist-info/METADATA
nonebot_plugin_wordle_daily-0.1.0.dist-info/license_files/LICENSE
nonebot_plugin_wordle_daily-0.1.0.dist-info/RECORD
